pyqt_color_picker/__init__.py
pyqt_color_picker/colorEditorWidget.py
pyqt_color_picker/colorHueBarWidget.py
pyqt_color_picker/colorPickerDialog.py
pyqt_color_picker/colorPickerWidget.py
pyqt_color_picker/colorSquareWidget.py
pyqt_color_picker/style/__init__.py
pyqt_color_picker/style/black_overlay.css
pyqt_color_picker/style/black_ring_of_color_selector.css
pyqt_color_picker/style/color_selector.css
pyqt_color_picker/style/hue_bg.css
pyqt_color_picker/style/hue_frame.css
pyqt_color_picker/style/hue_selector.css
pyqt_color_picker-0.0.20.dist-info/LICENSE
pyqt_color_picker-0.0.20.dist-info/METADATA
pyqt_color_picker-0.0.20.dist-info/WHEEL
pyqt_color_picker-0.0.20.dist-info/top_level.txt
pyqt_color_picker-0.0.20.dist-info/RECORD
