Metadata-Version: 2.1
Name: pyqt-color-picker
Version: 0.0.20
Summary: PyQt color picker dialog
Home-page: https://github.com/yjg30737/pyqt-color-picker.git
Author: Jung Gyu Yoon
Author-email: yjg30737@gmail.com
License: MIT
License-File: LICENSE
Requires-Dist: PyQt5 (>=5.8)
